L4/ARVORE.py
L4/__init__.py
L4/arvore2.py
L4/c45.py
L4/cart.py
L4/id3.py
arvoredecisao-0.1.0.dist-info/METADATA
arvoredecisao-0.1.0.dist-info/WHEEL
arvoredecisao-0.1.0.dist-info/top_level.txt
arvoredecisao-0.1.0.dist-info/RECORD
