Metadata-Version: 2.4
Name: arvoredecisao
Version: 0.1.0
Summary: Implementações de ID3, C4.5 e CART do zero
Author: Seu Nome
Author-email: Seu Nome <seuemail@email.com>
Requires-Dist: numpy
Requires-Dist: pandas
Dynamic: author
